MANIFEST.in
ez_setup.py
setup.cfg
setup.py
camlistore/__init__.py
camlistore/blobclient.py
camlistore/connection.py
camlistore/exceptions.py
camlistore/searchclient.py
camlistore.egg-info/PKG-INFO
camlistore.egg-info/SOURCES.txt
camlistore.egg-info/dependency_links.txt
camlistore.egg-info/requires.txt
camlistore.egg-info/top_level.txt