Metadata-Version: 1.1
Name: camlistore
Version: 0.0.1
Summary: Camlistore Client Library
Home-page: UNKNOWN
Author: Martin Atkins
Author-email: mart@degeneration.co.uk
License: UNKNOWN
Platform: UNKNOWN
Classifier: License :: OSI Approved :: MIT License
Classifier: Intended Audience :: Developers
